randnamepy/__init__.py
randnamepy/names.py
randnamepy/py.typed
randnamepy/usernames.py
randnamepy/utils.py
randnamepy-1.0.1.dist-info/licenses/LICENSE
randnamepy-1.0.1.dist-info/METADATA
randnamepy-1.0.1.dist-info/WHEEL
randnamepy-1.0.1.dist-info/top_level.txt
randnamepy-1.0.1.dist-info/RECORD
