Metadata-Version: 2.4
Name: randnamepy
Version: 1.0.1
Summary: A Python library for generating realistic random names, usernames, and placeholder data for testing purposes.
Author-email: Raj Gupta <rajgupta807633@gmail.com>
Maintainer-email: Raj Gupta <rajgupta807633@gmail.com>
License: MIT
Project-URL: Homepage, https://github.com/Raj9229/randname
Project-URL: Repository, https://github.com/Raj9229/randname
Project-URL: Issues, https://github.com/Raj9229/randname/issues
Keywords: random,name,generator,username,testing,placeholder,fake,mock,data
Classifier: Development Status :: 5 - Production/Stable
Classifier: Intended Audience :: Developers
Classifier: License :: OSI Approved :: MIT License
Classifier: Operating System :: OS Independent
Classifier: Programming Language :: Python :: 3
Classifier: Programming Language :: Python :: 3.8
Classifier: Programming Language :: Python :: 3.9
Classifier: Programming Language :: Python :: 3.10
Classifier: Programming Language :: Python :: 3.11
Classifier: Programming Language :: Python :: 3.12
Classifier: Topic :: Software Development :: Libraries :: Python Modules
Classifier: Topic :: Software Development :: Testing
Classifier: Topic :: Utilities
Classifier: Typing :: Typed
Requires-Python: >=3.8
License-File: LICENSE
Provides-Extra: dev
Requires-Dist: pytest>=7.0; extra == "dev"
Requires-Dist: pytest-cov>=4.0; extra == "dev"
Dynamic: license-file
